{"is_source_file": true, "format": "JavaScript/JSX", "description": "React component for sidebar navigation and note search in a note-taking web application.", "external_files": ["../context/NotesContext"], "external_methods": ["useNotes"], "published": [], "classes": [], "methods": [{"name": "Sidebar()", "description": "Functional React component rendering the sidebar with search and notes list.", "scope": "", "scopeKind": ""}], "calls": ["useNotes()", "actions.setQuery", "actions.createNote", "actions.selectNote", "new Date(note.updatedAt).toLocaleString()"], "search-terms": ["Sidebar", "NotesContext", "search box", "note list", "note selection", "React", "UI component", "notes filtering"], "state": 2, "file_id": 16, "knowledge_revision": 37, "git_revision": "", "ctags": [{"_type": "tag", "name": "Sidebar", "path": "/home/kavia/workspace/code-generation/secure-notes-web-application-15896-15905/notes_frontend/src/components/Sidebar.jsx", "pattern": "/^export default function Sidebar() {$/", "language": "JavaScript", "kind": "function", "signature": "()"}, {"_type": "tag", "name": "query", "path": "/home/kavia/workspace/code-generation/secure-notes-web-application-15896-15905/notes_frontend/src/components/Sidebar.jsx", "pattern": "/^            value={query}$/", "language": "JavaScript", "kind": "field", "scope": "Sidebar.value", "scopeKind": "class"}], "hash": "cf478bbaaee6f01067ea9729b2a4f41b", "format-version": 4, "code-base-name": "notes_frontend", "filename": "notes_frontend/src/components/Sidebar.jsx", "fields": [{"name": "value={query}", "scope": "Sidebar.value", "scopeKind": "class", "description": "unavailable"}], "revision_history": [{"37": ""}]}